evotech_bot/__init__.py
evotech_bot-0.1.0.dist-info/METADATA
evotech_bot-0.1.0.dist-info/WHEEL
evotech_bot-0.1.0.dist-info/RECORD
