Metadata-Version: 2.1
Name: evotech-bot
Version: 0.1.0
Summary: 
Author: Yossi Asher
Author-email: yossiasher@microsoft.com
Requires-Python: >=3.10,<4.0
Classifier: Programming Language :: Python :: 3
Classifier: Programming Language :: Python :: 3.10
Classifier: Programming Language :: Python :: 3.11
Requires-Dist: openai (>=0.28.0,<0.29.0)
Requires-Dist: requests (>=2.31.0,<3.0.0)
